i2c/i2c.v
module i2c_master (
    input clk,
    input start,
    input [6:0] addr,
    input [7:0] data,
    output reg scl = 1,  // Default high (idle)
    output reg sda = 1   // Default high (idle)
);
    reg [3:0] bit_cnt;
    reg [15:0] shift_reg;
    reg busy = 0;

    always @(posedge clk) begin
        if (start && !busy) begin
            busy <= 1;
            shift_reg <= {addr, 1'b0, data};  // Write bit = 0
            bit_cnt <= 15;
            scl <= 0;  // Start condition
            sda <= 0;
        end 
        else if (busy) begin
            scl <= ~scl;  // Toggle clock
            if (scl) begin
                sda <= shift_reg[bit_cnt];
                bit_cnt <= bit_cnt - 1;
            end
            if (bit_cnt == 0) busy <= 0;
        end
    end

    initial begin
        $dumpfile("i2c.vcd");
        $dumpvars(0, i2c_master);
    end
endmodule

i2c/i2c_master_sys/synthesis/tb_i2c.v
`timescale 1ns/1ps

module i2c_master_tb;

    reg clk = 0;
    reg start = 0;
    reg [6:0] addr = 7'b1010000;  // example slave address
    reg [7:0] data = 8'h5A;       // example data
    wire scl;
    wire sda;

    // Instantiate the I2C Master
    i2c_master uut (
        .clk(clk),
        .start(start),
        .addr(addr),
        .data(data),
        .scl(scl),
        .sda(sda)
    );

    // Clock generator
    always #5 clk = ~clk;

    initial begin
        // Dump VCD
        $dumpfile("i2c_master.vcd");
        $dumpvars(0, i2c_master_tb);

        // Wait for a few cycles
        #20;
        start = 1;    // Trigger I2C start condition
        #10;
        start = 0;    // Release start

        // Wait for transaction to complete
        #500;

        $finish;
    end
endmodule

i2c/i2c_master_sys/synthesis/i2c.vcd
$date
	Sun Apr  6 12:47:36 2025
$end
$version
	Icarus Verilog
$end
$timescale
	1ps
$end
$scope module i2c_master_tb $end
$scope module uut $end
$var wire 7 ! addr [6:0] $end
$var wire 1 " clk $end
$var wire 8 # data [7:0] $end
$var wire 1 $ start $end
$var reg 4 % bit_cnt [3:0] $end
$var reg 1 & busy $end
$var reg 1 ' scl $end
$var reg 1 ( sda $end
$var reg 16 ) shift_reg [15:0] $end
$upscope $end
$upscope $end
$scope module i2c_master_tb $end
$var wire 1 ( sda $end
$var wire 1 ' scl $end
$var reg 7 * addr [6:0] $end
$var reg 1 " clk $end
$var reg 8 + data [7:0] $end
$var reg 1 $ start $end
$scope module uut $end
$upscope $end
$upscope $end
$enddefinitions $end
$comment Show the parameter values. $end
$dumpall
$end
#0
$dumpvars
b1011010 +
b1010000 *
bx )
1(
1'
0&
bx %
0$
b1011010 #
0"
b1010000 !
$end
#5000
1"
#10000
0"
#15000
1"
#20000
0"
1$
#25000
0(
0'
b1111 %
b1010000001011010 )
1&
1"
#30000
0"
0$
#35000
1'
1"
#40000
0"
#45000
b1110 %
1(
0'
1"
#50000
0"
#55000
1'
1"
#60000
0"
#65000
b1101 %
0(
0'
1"
#70000
0"
#75000
1'
1"
#80000
0"
#85000
b1100 %
1(
0'
1"
#90000
0"
#95000
1'
1"
#100000
0"
#105000
b1011 %
0(
0'
1"
#110000
0"
#115000
1'
1"
#120000
0"
#125000
b1010 %
0'
1"
#130000
0"
#135000
1'
1"
#140000
0"
#145000
b1001 %
0'
1"
#150000
0"
#155000
1'
1"
#160000
0"
#165000
b1000 %
0'
1"
#170000
0"
#175000
1'
1"
#180000
0"
#185000
b111 %
0'
1"
#190000
0"
#195000
1'
1"
#200000
0"
#205000
b110 %
0'
1"
#210000
0"
#215000
1'
1"
#220000
0"
#225000
b101 %
1(
0'
1"
#230000
0"
#235000
1'
1"
#240000
0"
#245000
b100 %
0(
0'
1"
#250000
0"
#255000
1'
1"
#260000
0"
#265000
b11 %
1(
0'
1"
#270000
0"
#275000
1'
1"
#280000
0"
#285000
b10 %
0'
1"
#290000
0"
#295000
1'
1"
#300000
0"
#305000
b1 %
0(
0'
1"
#310000
0"
#315000
1'
1"
#320000
0"
#325000
b0 %
1(
0'
1"
#330000
0"
#335000
0&
1'
1"
