i2c/i2c.v
module i2c_master (
    input clk,
    input start,
    input [6:0] addr,
    input [7:0] data,
    output reg scl = 1,  // Default high (idle)
    output reg sda = 1   // Default high (idle)
);
    reg [3:0] bit_cnt;
    reg [15:0] shift_reg;
    reg busy = 0;

    always @(posedge clk) begin
        if (start && !busy) begin
            busy <= 1;
            shift_reg <= {addr, 1'b0, data};  // Write bit = 0
            bit_cnt <= 15;
            scl <= 0;  // Start condition
            sda <= 0;
        end 
        else if (busy) begin
            scl <= ~scl;  // Toggle clock
            if (scl) begin
                sda <= shift_reg[bit_cnt];
                bit_cnt <= bit_cnt - 1;
            end
            if (bit_cnt == 0) busy <= 0;
        end
    end

    initial begin
        $dumpfile("i2c.vcd");
        $dumpvars(0, i2c_master);
    end
endmodule

i2c/i2c.vcd
$date
	Tue Apr  8 11:58:41 2025
$end
$version
	Icarus Verilog
$end
$timescale
	1ps
$end
$scope module i2c_master $end
$var wire 7 ! addr [6:0] $end
$var wire 1 " clk $end
$var wire 8 # data [7:0] $end
$var wire 1 $ start $end
$var reg 4 % bit_cnt [3:0] $end
$var reg 1 & busy $end
$var reg 1 ' scl $end
$var reg 1 ( sda $end
$var reg 16 ) shift_reg [15:0] $end
$upscope $end
$enddefinitions $end
$comment Show the parameter values. $end
$dumpall
$end
#0
$dumpvars
bx )
1(
1'
0&
bx %
0$
b10001 #
1"
b110000 !
$end
#5000
0"
#10000
1$
1"
#15000
0"
#20000
0$
0(
0'
b1111 %
b110000000010001 )
1&
1"
#25000
0"
#30000
1'
1"
#35000
0"
#40000
b1110 %
0'
1"
#45000
0"
#50000
1'
1"
#55000
0"
#60000
b1101 %
1(
0'
1"
#65000
0"
#70000
1'
1"
#75000
0"
#80000
b1100 %
0'
1"
#85000
0"
#90000
1'
1"
#95000
0"
#100000
b1011 %
0(
0'
1"
#105000
0"
#110000
1'
1"
#115000
0"
#120000
b1010 %
0'
1"
#125000
0"
#130000
1'
1"
#135000
0"
#140000
b1001 %
0'
1"
#145000
0"
#150000
1'
1"
#155000
0"
#160000
b1000 %
0'
1"
#165000
0"
#170000
1'
1"
#175000
0"
#180000
b111 %
0'
1"
#185000
0"
#190000
1'
1"
#195000
0"
#200000
b110 %
0'
1"
#205000
0"
#210000
1'
1"
#215000
0"
#220000
b100010 #
b110001 !
b101 %
0'
1"
#225000
0"
#230000
1$
1'
1"
#235000
0"
#240000
0$
b100 %
0'
1"
#245000
0"
#250000
1'
1"
#255000
0"
#260000
b11 %
1(
0'
1"
#265000
0"
#270000
1'
1"
#275000
0"
#280000
b10 %
0(
0'
1"
#285000
0"
#290000
1'
1"
#295000
0"
#300000
b1 %
0'
1"
#305000
0"
#310000
1'
1"
#315000
0"
#320000
b0 %
0'
1"
#325000
0"
#330000
0&
1'
1"
#335000
0"
#340000
1"
#345000
0"
#350000
1"
#355000
0"
#360000
1"
#365000
0"
#370000
1"
#375000
0"
#380000
1"
#385000
0"
#390000
1"
#395000
0"
#400000
1"
#405000
0"
#410000
1"
#415000
0"
#420000
1"
#425000
0"
#430000
1"
#435000
0"
#440000
b110011 #
b110010 !
1"
#445000
0"
#450000
1$
1"
#455000
0"
#460000
0$
0'
b1111 %
b110010000110011 )
1&
1"
#465000
0"
#470000
1'
1"
#475000
0"
#480000
b1110 %
0'
1"
#485000
0"
#490000
1'
1"
#495000
0"
#500000
b1101 %
1(
0'
1"
#505000
0"
#510000
1'
1"
#515000
0"
#520000
b1100 %
0'
1"
#525000
0"
#530000
1'
1"
#535000
0"
#540000
b1011 %
0(
0'
1"
#545000
0"
#550000
1'
1"
#555000
0"
#560000
b1010 %
0'
1"
#565000
0"
#570000
1'
1"
#575000
0"
#580000
b1001 %
1(
0'
1"
#585000
0"
#590000
1'
1"
#595000
0"
#600000
b1000 %
0(
0'
1"
#605000
0"
#610000
1'
1"
#615000
0"
#620000
b111 %
0'
1"
#625000
0"
#630000
1'
1"
#635000
0"
#640000
b110 %
0'
1"
#645000
0"
#650000
1'
1"
#655000
0"
#660000
b101 %
0'
1"
#660001
b11111111 #
b1111111 !
#665001
0"
#670001
1$
1'
1"
#675001
0"
#680001
0$
b100 %
1(
0'
1"
#685001
0"
#690001
1'
1"
#695001
0"
#700001
b11 %
0'
1"
#705001
0"
#710001
1'
1"
#715001
0"
#720001
b10 %
0(
0'
1"
#725001
0"
#730001
1'
1"
#735001
0"
#740001
b1 %
0'
1"
#745001
0"
#750001
1'
1"
#755001
0"
#760001
b0 %
1(
0'
1"
#765001
0"
#770001
0&
1'
1"
