UART/results/netlist.v
/* Generated by Yosys 0.9 (git sha1 1979e0b) */

(* top =  1  *)
(* src = "uart_tx.v:1" *)
module uart_tx(clk, start, data, tx, done);
  (* src = "uart_tx.v:15" *)
  wire [3:0] _000_;
  (* src = "uart_tx.v:15" *)
  wire [3:0] _001_;
  (* src = "uart_tx.v:15" *)
  wire _002_;
  (* src = "uart_tx.v:15" *)
  wire _003_;
  (* src = "uart_tx.v:15" *)
  wire [9:0] _004_;
  (* src = "uart_tx.v:15" *)
  wire _005_;
  wire _006_;
  wire _007_;
  wire _008_;
  wire _009_;
  wire _010_;
  wire _011_;
  wire _012_;
  wire _013_;
  wire _014_;
  wire _015_;
  wire _016_;
  wire _017_;
  wire _018_;
  wire _019_;
  wire _020_;
  wire _021_;
  wire _022_;
  wire _023_;
  wire _024_;
  wire _025_;
  wire _026_;
  wire _027_;
  wire _028_;
  wire _029_;
  wire _030_;
  wire _031_;
  wire _032_;
  wire _033_;
  wire _034_;
  wire _035_;
  wire _036_;
  wire _037_;
  wire _038_;
  wire _039_;
  wire _040_;
  wire _041_;
  wire _042_;
  wire _043_;
  wire _044_;
  wire _045_;
  wire _046_;
  wire _047_;
  wire _048_;
  wire _049_;
  wire _050_;
  wire _051_;
  wire _052_;
  wire _053_;
  wire _054_;
  wire _055_;
  wire _056_;
  wire _057_;
  wire _058_;
  wire _059_;
  wire _060_;
  wire _061_;
  wire _062_;
  wire _063_;
  wire _064_;
  wire _065_;
  wire _066_;
  wire _067_;
  wire _068_;
  wire _069_;
  wire _070_;
  wire _071_;
  wire _072_;
  wire _073_;
  wire _074_;
  wire _075_;
  (* src = "uart_tx.v:12" *)
  reg [3:0] baud_cnt;
  (* src = "uart_tx.v:10" *)
  reg [3:0] bit_cnt;
  (* init = 1'h0 *)
  (* src = "uart_tx.v:13" *)
  reg busy = 1'h0;
  (* src = "uart_tx.v:2" *)
  input clk;
  (* src = "uart_tx.v:4" *)
  input [7:0] data;
  (* src = "uart_tx.v:6" *)
  output done;
  reg done;
  (* src = "uart_tx.v:11" *)
  reg [9:0] shift_reg;
  (* src = "uart_tx.v:3" *)
  input start;
  (* init = 1'h1 *)
  (* src = "uart_tx.v:5" *)
  output tx;
  reg tx = 1'h1;
  assign _035_ = ~busy;
  assign _036_ = baud_cnt[0] & ~(baud_cnt[1]);
  assign _037_ = baud_cnt[2] | ~(baud_cnt[3]);
  assign _038_ = _036_ & ~(_037_);
  assign _039_ = _038_ ? shift_reg[0] : tx;
  assign _040_ = busy ? _039_ : tx;
  assign _041_ = start & ~(busy);
  assign _005_ = _041_ ? tx : _040_;
  assign _042_ = ~_038_;
  assign _043_ = ~(bit_cnt[1] | bit_cnt[0]);
  assign _044_ = bit_cnt[3] | bit_cnt[2];
  assign _045_ = _044_ | ~(_043_);
  assign _046_ = _045_ ^ bit_cnt[0];
  assign _047_ = _038_ ? _046_ : bit_cnt[0];
  assign _048_ = busy ? _047_ : bit_cnt[0];
  assign _001_[0] = _048_ | _041_;
  assign _049_ = ~_041_;
  assign _050_ = ~bit_cnt[1];
  assign _051_ = _043_ & ~(_044_);
  assign _052_ = bit_cnt[1] ^ bit_cnt[0];
  assign _053_ = _051_ ? _050_ : _052_;
  assign _054_ = _038_ ? _053_ : _050_;
  assign _055_ = busy ? _054_ : _050_;
  assign _001_[1] = _049_ & ~(_055_);
  assign _056_ = ~bit_cnt[2];
  assign _057_ = bit_cnt[1] | bit_cnt[0];
  assign _058_ = _057_ ^ bit_cnt[2];
  assign _059_ = _051_ ? _056_ : _058_;
  assign _060_ = _038_ ? _059_ : _056_;
  assign _061_ = busy ? _060_ : _056_;
  assign _001_[2] = _049_ & ~(_061_);
  assign _062_ = _056_ & ~(_057_);
  assign _063_ = _062_ ^ bit_cnt[3];
  assign _064_ = _051_ ? bit_cnt[3] : _063_;
  assign _065_ = _038_ ? _064_ : bit_cnt[3];
  assign _066_ = busy ? _065_ : bit_cnt[3];
  assign _001_[3] = _066_ | _041_;
  assign _067_ = ~done;
  assign _068_ = ~((_051_ & _038_) | done);
  assign _069_ = busy ? _068_ : _067_;
  assign _003_ = _049_ & ~(_069_);
  assign _070_ = ~baud_cnt[0];
  assign _071_ = _038_ | baud_cnt[0];
  assign _072_ = busy ? _071_ : _070_;
  assign _000_[0] = ~(_072_ | _041_);
  assign _073_ = baud_cnt[1] & ~(baud_cnt[0]);
  assign _074_ = _036_ ? _037_ : _073_;
  assign _075_ = busy ? _074_ : baud_cnt[1];
  assign _000_[1] = _075_ & ~(_041_);
  assign _006_ = ~(baud_cnt[0] & baud_cnt[1]);
  assign _007_ = ~(_006_ ^ baud_cnt[2]);
  assign _008_ = _007_ & ~(_038_);
  assign _009_ = busy ? _008_ : baud_cnt[2];
  assign _000_[2] = _009_ & ~(_041_);
  assign _010_ = ~baud_cnt[3];
  assign _011_ = baud_cnt[2] & ~(_006_);
  assign _012_ = _011_ ^ _010_;
  assign _013_ = _012_ | _038_;
  assign _014_ = busy ? _013_ : _010_;
  assign _000_[3] = _049_ & ~(_014_);
  assign _015_ = _038_ ? shift_reg[1] : shift_reg[0];
  assign _016_ = busy ? _015_ : shift_reg[0];
  assign _004_[0] = _016_ & ~(_041_);
  assign _017_ = _038_ ? shift_reg[2] : shift_reg[1];
  assign _018_ = busy ? _017_ : shift_reg[1];
  assign _004_[1] = _041_ ? data[0] : _018_;
  assign _019_ = _038_ ? shift_reg[3] : shift_reg[2];
  assign _020_ = busy ? _019_ : shift_reg[2];
  assign _004_[2] = _041_ ? data[1] : _020_;
  assign _021_ = _038_ ? shift_reg[4] : shift_reg[3];
  assign _022_ = busy ? _021_ : shift_reg[3];
  assign _004_[3] = _041_ ? data[2] : _022_;
  assign _023_ = _038_ ? shift_reg[5] : shift_reg[4];
  assign _024_ = busy ? _023_ : shift_reg[4];
  assign _004_[4] = _041_ ? data[3] : _024_;
  assign _025_ = _038_ ? shift_reg[6] : shift_reg[5];
  assign _026_ = busy ? _025_ : shift_reg[5];
  assign _004_[5] = _041_ ? data[4] : _026_;
  assign _027_ = _038_ ? shift_reg[7] : shift_reg[6];
  assign _028_ = busy ? _027_ : shift_reg[6];
  assign _004_[6] = _041_ ? data[5] : _028_;
  assign _029_ = _038_ ? shift_reg[8] : shift_reg[7];
  assign _030_ = busy ? _029_ : shift_reg[7];
  assign _004_[7] = _041_ ? data[6] : _030_;
  assign _031_ = _038_ ? shift_reg[9] : shift_reg[8];
  assign _032_ = busy ? _031_ : shift_reg[8];
  assign _004_[8] = _041_ ? data[7] : _032_;
  assign _033_ = ~((_042_ | _035_) & shift_reg[9]);
  assign _004_[9] = ~(_033_ & _049_);
  assign _034_ = ~(_051_ & _038_);
  assign _002_ = busy ? _034_ : start;
  (* src = "uart_tx.v:15" *)
  always @(posedge clk)
      shift_reg[0] <= _004_[0];
  (* src = "uart_tx.v:15" *)
  always @(posedge clk)
      shift_reg[1] <= _004_[1];
  (* src = "uart_tx.v:15" *)
  always @(posedge clk)
      shift_reg[2] <= _004_[2];
  (* src = "uart_tx.v:15" *)
  always @(posedge clk)
      shift_reg[3] <= _004_[3];
  (* src = "uart_tx.v:15" *)
  always @(posedge clk)
      shift_reg[4] <= _004_[4];
  (* src = "uart_tx.v:15" *)
  always @(posedge clk)
      shift_reg[5] <= _004_[5];
  (* src = "uart_tx.v:15" *)
  always @(posedge clk)
      shift_reg[6] <= _004_[6];
  (* src = "uart_tx.v:15" *)
  always @(posedge clk)
      shift_reg[7] <= _004_[7];
  (* src = "uart_tx.v:15" *)
  always @(posedge clk)
      shift_reg[8] <= _004_[8];
  (* src = "uart_tx.v:15" *)
  always @(posedge clk)
      shift_reg[9] <= _004_[9];
  (* src = "uart_tx.v:15" *)
  always @(posedge clk)
      baud_cnt[0] <= _000_[0];
  (* src = "uart_tx.v:15" *)
  always @(posedge clk)
      baud_cnt[1] <= _000_[1];
  (* src = "uart_tx.v:15" *)
  always @(posedge clk)
      baud_cnt[2] <= _000_[2];
  (* src = "uart_tx.v:15" *)
  always @(posedge clk)
      baud_cnt[3] <= _000_[3];
  (* src = "uart_tx.v:15" *)
  always @(posedge clk)
      busy <= _002_;
  (* src = "uart_tx.v:15" *)
  always @(posedge clk)
      done <= _003_;
  (* src = "uart_tx.v:15" *)
  always @(posedge clk)
      bit_cnt[0] <= _001_[0];
  (* src = "uart_tx.v:15" *)
  always @(posedge clk)
      bit_cnt[1] <= _001_[1];
  (* src = "uart_tx.v:15" *)
  always @(posedge clk)
      bit_cnt[2] <= _001_[2];
  (* src = "uart_tx.v:15" *)
  always @(posedge clk)
      bit_cnt[3] <= _001_[3];
  (* src = "uart_tx.v:15" *)
  always @(posedge clk)
      tx <= _005_;
endmodule

UART/results/wave.vcd
$date
	Tue Apr  8 11:47:02 2025
$end
$version
	Icarus Verilog
$end
$timescale
	1ps
$end
$scope module uart_tx $end
$var wire 1 ! clk $end
$var wire 8 " data [7:0] $end
$var wire 1 # start $end
$var reg 4 $ baud_cnt [3:0] $end
$var reg 4 % bit_cnt [3:0] $end
$var reg 1 & busy $end
$var reg 1 ' done $end
$var reg 10 ( shift_reg [9:0] $end
$var reg 1 ) tx $end
$upscope $end
$enddefinitions $end
#0
$dumpvars
1)
bx (
x'
0&
bx %
bx $
0#
b1010101 "
0!
$end
#5000
1!
#10000
0!
1#
#15000
0#
0'
1&
b0 $
b1001 %
b1010101010 (
1!
#20000
0!
#25000
b1 $
1!
#30000
0!
#35000
b10 $
1!
#40000
0!
#45000
b11 $
1!
#50000
0!
#55000
b100 $
1!
#60000
0!
#65000
b101 $
1!
#70000
0!
#75000
b110 $
1!
#80000
0!
#85000
b111 $
1!
#90000
0!
#95000
b1000 $
1!
#100000
0!
#105000
b1001 $
1!
#110000
0!
#115000
b1000 %
b0 $
b101010101 (
0)
1!
#120000
0!
#125000
b1 $
1!
#130000
0!
#135000
b10 $
1!
#140000
0!
#145000
b11 $
1!
#150000
0!
#155000
b100 $
1!
#160000
0!
#165000
b101 $
1!
#170000
0!
#175000
b110 $
1!
#180000
0!
#185000
b111 $
1!
#190000
0!
#195000
b1000 $
1!
#200000
0!
#205000
b1001 $
1!
#210000
0!
#215000
b111 %
b0 $
b10101010 (
1)
1!
#220000
0!
#225000
b1 $
1!
#230000
0!
#235000
b10 $
1!
#240000
0!
#245000
b11 $
1!
#250000
0!
#255000
b100 $
1!
#260000
0!
#265000
b101 $
1!
#270000
0!
#275000
b110 $
1!
#280000
0!
#285000
b111 $
1!
#290000
0!
#295000
b1000 $
1!
#300000
0!
#305000
b1001 $
1!
#310000
0!
#315000
b110 %
b0 $
b1010101 (
0)
1!
#320000
0!
#325000
b1 $
1!
#330000
0!
#335000
b10 $
1!
#340000
0!
#345000
b11 $
1!
#350000
0!
#355000
b100 $
1!
#360000
0!
#365000
b101 $
1!
#370000
0!
#375000
b110 $
1!
#380000
0!
#385000
b111 $
1!
#390000
0!
#395000
b1000 $
1!
#400000
0!
#405000
b1001 $
1!
#410000
0!
#415000
b101 %
b0 $
b101010 (
1)
1!
#420000
0!
#425000
b1 $
1!
#430000
0!
#435000
b10 $
1!
#440000
0!
#445000
b11 $
1!
#450000
0!
#455000
b100 $
1!
#460000
0!
#465000
b101 $
1!
#470000
0!
#475000
b110 $
1!
#480000
0!
#485000
b111 $
1!
#490000
0!
#495000
b1000 $
1!
#500000
0!
#505000
b1001 $
1!
#510000
0!
#515000
b100 %
b0 $
b10101 (
0)
1!
#520000
0!
#525000
b1 $
1!
#530000
0!
#535000
b10 $
1!
#540000
0!
#545000
b11 $
1!
#550000
0!
#555000
b100 $
1!
#560000
0!
#565000
b101 $
1!
#570000
0!
#575000
b110 $
1!
#580000
0!
#585000
b111 $
1!
#590000
0!
#595000
b1000 $
1!
#600000
0!
#605000
b1001 $
1!
#610000
0!
#615000
b11 %
b0 $
b1010 (
1)
1!
#620000
0!
#625000
b1 $
1!
#630000
0!
#635000
b10 $
1!
#640000
0!
#645000
b11 $
1!
#650000
0!
#655000
b100 $
1!
#660000
0!
#665000
b101 $
1!
#670000
0!
#675000
b110 $
1!
#680000
0!
#685000
b111 $
1!
#690000
0!
#695000
b1000 $
1!
#700000
0!
#705000
b1001 $
1!
#710000
0!
#715000
b10 %
b0 $
b101 (
0)
1!
#720000
0!
#725000
b1 $
1!
#730000
0!
#735000
b10 $
1!
#740000
0!
#745000
b11 $
1!
#750000
0!
#755000
b100 $
1!
#760000
0!
#765000
b101 $
1!
#770000
0!
#775000
b110 $
1!
#780000
0!
#785000
b111 $
1!
#790000
0!
#795000
b1000 $
1!
#800000
0!
#805000
b1001 $
1!
#810000
0!
#815000
b1 %
b0 $
b10 (
1)
1!
#820000
0!
#825000
b1 $
1!
#830000
0!
#835000
b10 $
1!
#840000
0!
#845000
b11 $
1!
#850000
0!
#855000
b100 $
1!
#860000
0!
#865000
b101 $
1!
#870000
0!
#875000
b110 $
1!
#880000
0!
#885000
b111 $
1!
#890000
0!
#895000
b1000 $
1!
#900000
0!
#905000
b1001 $
1!
#910000
0!
#915000
b0 %
b0 $
b1 (
0)
1!
#920000
0!
#925000
b1 $
1!
#930000
0!
#935000
b10 $
1!
#940000
0!
#945000
b11 $
1!
#950000
0!
#955000
b100 $
1!
#960000
0!
#965000
b101 $
1!
#970000
0!
#975000
b110 $
1!
#980000
0!
#985000
b111 $
1!
#990000
0!
#995000
b1000 $
1!
#1000000
0!
#1005000
b1001 $
1!
#1010000
0!
#1015000
1'
0&
b0 $
b0 (
1)
1!
